{
    "author": "Maxime Mangel",
    "classifications": [
        "Fable",
        "Elmish",
        "React"
    ],
    "name": "Fable.Elmish.React.Demo App",
    "tags": {
        "language": "F#",
        "type": "project"
    },
    "symbols": {
        "yarn": {
            "type": "parameter",
            "dataType": "bool",
            "defaultValue": "false",
            "description": "If set then, the template will be configure to use yarn."
        }
    },
    "sources": [
        {
            "modifiers": [
                {
                    "condition": "(!yarn)",
                    "exclude": [
                        "yarn.lock"
                    ]
                },
                {
                    "condition": "(yarn)",
                    "exclude": [
                        "package-lock.json"
                    ]
                }
            ]
        }
    ],
    "identity": "Fable.Template.Elmish.React.Demo",
    "groupIdentity": "FableElmishReactDemo",
    "shortName": "fable-elmish-react-demo",
    "sourceName": "FableElmishReactDemoTemplate",
    // This allows using the `-n` option to create a new directory
    "preferNameDirectory": true
}
